taskgroups.py
taskgroups-0.0.0a0.dist-info/LICENSE
taskgroups-0.0.0a0.dist-info/WHEEL
taskgroups-0.0.0a0.dist-info/METADATA
taskgroups-0.0.0a0.dist-info/RECORD
