Metadata-Version: 2.1
Name: taskgroups
Version: 0.0.0a0
Summary: did you mean taskgroup - without an s?
Author-email: Thomas Grainger <taskgroup@graingert.co.uk>
Classifier: License :: OSI Approved :: MIT License
Requires-Dist: taskgroup
Project-URL: Home, https://github.com/graingert/taskgroup
